Artesian/.gitignore
Artesian/ArtesianConfig.py
Artesian/ArtesianPolicyConfig.py
Artesian/Exceptions.py
Artesian/Granularity.py
Artesian/__init__.py
Artesian/_version.py
Artesian/GMEPublicOffers/ExtractionRangeConfig.py
Artesian/GMEPublicOffers/GMEPublicOfferQuery.py
Artesian/GMEPublicOffers/GMEPublicOfferQueryParameters.py
Artesian/GMEPublicOffers/GMEPublicOfferService.py
Artesian/GMEPublicOffers/__init__.py
Artesian/GMEPublicOffers/_Enum/BaType.py
Artesian/GMEPublicOffers/_Enum/GenerationType.py
Artesian/GMEPublicOffers/_Enum/Market.py
Artesian/GMEPublicOffers/_Enum/Purpose.py
Artesian/GMEPublicOffers/_Enum/Scope.py
Artesian/GMEPublicOffers/_Enum/Status.py
Artesian/GMEPublicOffers/_Enum/UnitType.py
Artesian/GMEPublicOffers/_Enum/Zone.py
Artesian/GMEPublicOffers/_Enum/__init__.py
Artesian/MarketData/CommonUnitOfMeasure.py
Artesian/MarketData/MarketDataService.py
Artesian/MarketData/__init__.py
Artesian/MarketData/_Dto/ArtesianMetadataFacet.py
Artesian/MarketData/_Dto/ArtesianSearchResults.py
Artesian/MarketData/_Dto/CheckConversionResult.py
Artesian/MarketData/_Dto/CurveRangeEntity.py
Artesian/MarketData/_Dto/DeleteData.py
Artesian/MarketData/_Dto/DerivedCfg.py
Artesian/MarketData/_Dto/MarketDataEntityInput.py
Artesian/MarketData/_Dto/MarketDataEntityOutput.py
Artesian/MarketData/_Dto/MarketDataIdentifier.py
Artesian/MarketData/_Dto/PagedResult.py
Artesian/MarketData/_Dto/UnitOfMeasure.py
Artesian/MarketData/_Dto/UpsertData.py
Artesian/MarketData/_Dto/__init__.py
Artesian/MarketData/_Enum/AggregationRule.py
Artesian/MarketData/_Enum/ArtesianMetadataFacetType.py
Artesian/MarketData/_Enum/DerivedAlgorithm.py
Artesian/MarketData/_Enum/MarketDataType.py
Artesian/MarketData/_Enum/__init__.py
Artesian/Query/ActualQuery.py
Artesian/Query/AuctionQuery.py
Artesian/Query/BidAskQuery.py
Artesian/Query/DefaultPartitionStrategy.py
Artesian/Query/MasQuery.py
Artesian/Query/QueryService.py
Artesian/Query/RelativeInterval.py
Artesian/Query/VersionedQuery.py
artesian_sdk-4.2.1.dist-info/licenses/LICENSE
artesian_sdk-4.2.1.dist-info/METADATA
artesian_sdk-4.2.1.dist-info/WHEEL
artesian_sdk-4.2.1.dist-info/top_level.txt
artesian_sdk-4.2.1.dist-info/RECORD
