Metadata-Version: 2.4
Name: artesian-sdk
Version: 4.2.1
Summary: Library provides read access to the Artesian API
Author-email: ARK Lab <arklab@ark-energy.eu>
Maintainer-email: ARK Lab <arklab@ark-energy.eu>
License: MIT License
Project-URL: Homepage, https://www.artesian.cloud/
Project-URL: Source, https://github.com/ARKlab/Artesian.SDK-Python
Keywords: Artesian
Classifier: License :: OSI Approved :: MIT License
Classifier: Operating System :: OS Independent
Classifier: Programming Language :: Python :: 3.8
Classifier: Programming Language :: Python :: 3.9
Classifier: Programming Language :: Python :: 3.10
Classifier: Programming Language :: Python :: 3.11
Requires-Python: >=3.8
License-File: LICENSE
Requires-Dist: requests~=2.27
Requires-Dist: six~=1.16
Requires-Dist: jsons>=1.6.1,~=1.6
Requires-Dist: python-dateutil>=2.8.2,~=2.8
Provides-Extra: dev
Requires-Dist: responses~=0.22; extra == "dev"
Requires-Dist: flake8; extra == "dev"
Requires-Dist: flake8-annotations; extra == "dev"
Requires-Dist: pytest; extra == "dev"
Requires-Dist: pytest-cov; extra == "dev"
Requires-Dist: twine; extra == "dev"
Requires-Dist: build; extra == "dev"
Requires-Dist: black; extra == "dev"
Dynamic: license-file
